kagiso_sitemap/__init__.py
kagiso_sitemap/sitemaps.py
kagiso_sitemap/urls.py
kagiso_sitemap/templates/kagiso_sitemap/kagiso_sitemap.xml
kagiso_sitemap/tests/__init__.py
kagiso_sitemap/tests/test_sitemaps.py
kagiso_sitemap/tests/urls.py
kagiso_sitemap/tests/settings/__init__.py
kagiso_sitemap/tests/settings/test.py
kagiso_sitemap-3.0.0.dist-info/DESCRIPTION.rst
kagiso_sitemap-3.0.0.dist-info/METADATA
kagiso_sitemap-3.0.0.dist-info/metadata.json
kagiso_sitemap-3.0.0.dist-info/RECORD
kagiso_sitemap-3.0.0.dist-info/top_level.txt
kagiso_sitemap-3.0.0.dist-info/WHEEL
