Metadata-Version: 2.0
Name: kagiso-sitemap
Version: 3.0.0
Summary: Kagiso Sitemap
Home-page: https://github.com/Kagiso-Future-Media/kagiso_sitemap
Author: Kagiso Media
Author-email: development@kagiso.io
License: UNKNOWN
Platform: UNKNOWN
Requires-Dist: wagtail (>=1.8.0)
